auto_file/__init__.py
auto_file/extra.py
auto_file/function.py
auto_file/python.py
auto_file-2.0.dist-info/LICENSE
auto_file-2.0.dist-info/METADATA
auto_file-2.0.dist-info/WHEEL
auto_file-2.0.dist-info/top_level.txt
auto_file-2.0.dist-info/RECORD
