Metadata-Version: 2.1
Name: auto-file
Version: 2.0
Summary: a module that can make all required folder and files for making python library and also genrate files for normal use
Home-page: https://github.com/Tech-with-anmol/pdftotexthttps://github.com/Tech-with-anmol/auto-file
Author: Anmol.py
Author-email: anmollklfh@gmail.com
License: MIT
Keywords: file
Platform: UNKNOWN
Classifier: Development Status :: 5 - Production/Stable
Classifier: Intended Audience :: Education
Classifier: Operating System :: Microsoft :: Windows :: Windows 10
Classifier: License :: OSI Approved :: MIT License
Classifier: Programming Language :: Python :: 3
